fdc/__init__.py
fdc/datatypes/AbridgedFood.py
fdc/datatypes/AbridgedFoodNutrient.py
fdc/datatypes/BrandedFood.py
fdc/datatypes/ExperimentalFood.py
fdc/datatypes/Food.py
fdc/datatypes/FoodAttribute.py
fdc/datatypes/FoodAttributeType.py
fdc/datatypes/FoodCategory.py
fdc/datatypes/FoodComponent.py
fdc/datatypes/FoodGroup.py
fdc/datatypes/FoodNutrient.py
fdc/datatypes/FoodNutrientDerivation.py
fdc/datatypes/FoodNutrientSource.py
fdc/datatypes/FoodPortion.py
fdc/datatypes/FoodSearchCriteria.py
fdc/datatypes/FoodUpdateLog.py
fdc/datatypes/FoundationFood.py
fdc/datatypes/InputFood.py
fdc/datatypes/InputFoodSurvey.py
fdc/datatypes/InputFoods.py
fdc/datatypes/LabelNutrient.py
fdc/datatypes/MarketAcquisitionFood.py
fdc/datatypes/MeasureUnit.py
fdc/datatypes/Nutrient.py
fdc/datatypes/NutrientAcquisitionDetails.py
fdc/datatypes/NutrientAnalysisDetails.py
fdc/datatypes/NutrientConversionFactor.py
fdc/datatypes/RetentionFactor.py
fdc/datatypes/SRLegacyFood.py
fdc/datatypes/SampleFood.py
fdc/datatypes/SearchResult.py
fdc/datatypes/SearchResultFood.py
fdc/datatypes/SurveyFood.py
fdc/datatypes/WweiaFoodCategory.py
fdc/datatypes/__init__.py
fdc/fdc.py
py_fdc/__init__.py
py_usda_fdc-0.2.0.dist-info/METADATA
py_usda_fdc-0.2.0.dist-info/WHEEL
py_usda_fdc-0.2.0.dist-info/licenses/LICENSE
py_usda_fdc-0.2.0.dist-info/RECORD
