Metadata-Version: 2.1
Name: py-usda-fdc
Version: 0.2.0
Author: Patrick Stephane Tawil
Author-Email: Patrick S. Tawil <patricktawil1@hotmail.com>
License: GPL
Project-URL: Homepage, https://github.com/ghostiek/py-fdc
Project-URL: Issues, https://github.com/ghostiek/py-fdc/issues
Requires-Python: >=3.10
Requires-Dist: requests>=2.31.0
Requires-Dist: pyhumps>=3.8.0
